score.js-0.4.8-py3.7-nspkg.pth
score/js/__init__.py
score/js/_init.py
score/js/minifier.py
score.js-0.4.8.dist-info/COPYING.LESSER.txt
score.js-0.4.8.dist-info/METADATA
score.js-0.4.8.dist-info/WHEEL
score.js-0.4.8.dist-info/namespace_packages.txt
score.js-0.4.8.dist-info/top_level.txt
score.js-0.4.8.dist-info/RECORD
