Metadata-Version: 2.1
Name: score.js
Version: 0.4.8
Summary: Helpers for managing javascript with The SCORE Framework
Home-page: http://score-framework.org
Author: strg.at
Author-email: score@strg.at
License: LGPL
Keywords: score framework web javascript
Platform: UNKNOWN
Classifier: Development Status :: 4 - Beta
Classifier: Environment :: Console
Classifier: Environment :: Web Environment
Classifier: Framework :: Pyramid
Classifier: Intended Audience :: Developers
Classifier: License :: OSI Approved :: GNU Lesser General Public License v3 or later (LGPLv3+)
Classifier: Operating System :: OS Independent
Classifier: Programming Language :: Python :: 3
Classifier: Programming Language :: Python :: 3.4
Classifier: Programming Language :: Python :: 3.5
Classifier: Topic :: Software Development :: Libraries :: Application Frameworks
Requires-Dist: score.webassets (>=0.3.22)
